{
  "formatVersion": 1,
  "database": {
    "version": 1,
    "identityHash": "87993c75a1c7106805064f9eed33c9aa",
    "entities": [
      {
        "tableName": "scan_results",
        "createSql": "CREATE TABLE IF NOT EXISTS `${TABLE_NAME}` (`scanId` TEXT NOT NULL, `skillName` TEXT NOT NULL, `skillVersion` TEXT, `overallStatus` TEXT NOT NULL, `riskScore` INTEGER NOT NULL, `scannedFiles` INTEGER NOT NULL, `scanDurationMs` INTEGER NOT NULL, `findingsCount` INTEGER NOT NULL, `scanTimestamp` INTEGER NOT NULL, `note` TEXT, PRIMARY KEY(`scanId`))",
        "fields": [
          {
            "fieldPath": "scanId",
            "columnName": "scanId",
            "affinity": "TEXT",
            "notNull": true
          },
          {
            "fieldPath": "skillName",
            "columnName": "skillName",
            "affinity": "TEXT",
            "notNull": true
          },
          {
            "fieldPath": "skillVersion",
            "columnName": "skillVersion",
            "affinity": "TEXT",
            "notNull": false
          },
          {
            "fieldPath": "overallStatus",
            "columnName": "overallStatus",
            "affinity": "TEXT",
            "notNull": true
          },
          {
            "fieldPath": "riskScore",
            "columnName": "riskScore",
            "affinity": "INTEGER",
            "notNull": true
          },
          {
            "fieldPath": "scannedFiles",
            "columnName": "scannedFiles",
            "affinity": "INTEGER",
            "notNull": true
          },
          {
            "fieldPath": "scanDurationMs",
            "columnName": "scanDurationMs",
            "affinity": "INTEGER",
            "notNull": true
          },
          {
            "fieldPath": "findingsCount",
            "columnName": "findingsCount",
            "affinity": "INTEGER",
            "notNull": true
          },
          {
            "fieldPath": "scanTimestamp",
            "columnName": "scanTimestamp",
            "affinity": "INTEGER",
            "notNull": true
          },
          {
            "fieldPath": "note",
            "columnName": "note",
            "affinity": "TEXT",
            "notNull": false
          }
        ],
        "primaryKey": {
          "autoGenerate": false,
          "columnNames": [
            "scanId"
          ]
        },
        "indices": [],
        "foreignKeys": []
      },
      {
        "tableName": "security_findings",
        "createSql": "CREATE TABLE IF NOT EXISTS `${TABLE_NAME}` (`scanId` TEXT NOT NULL, `findingIndex` INTEGER NOT NULL, `severity` TEXT NOT NULL, `category` TEXT NOT NULL, `title` TEXT NOT NULL, `description` TEXT NOT NULL, `affectedFile` TEXT, `affectedLine` INTEGER, `recommendation` TEXT NOT NULL, `cveId` TEXT, PRIMARY KEY(`scanId`, `findingIndex`))",
        "fields": [
          {
            "fieldPath": "scanId",
            "columnName": "scanId",
            "affinity": "TEXT",
            "notNull": true
          },
          {
            "fieldPath": "findingIndex",
            "columnName": "findingIndex",
            "affinity": "INTEGER",
            "notNull": true
          },
          {
            "fieldPath": "severity",
            "columnName": "severity",
            "affinity": "TEXT",
            "notNull": true
          },
          {
            "fieldPath": "category",
            "columnName": "category",
            "affinity": "TEXT",
            "notNull": true
          },
          {
            "fieldPath": "title",
            "columnName": "title",
            "affinity": "TEXT",
            "notNull": true
          },
          {
            "fieldPath": "description",
            "columnName": "description",
            "affinity": "TEXT",
            "notNull": true
          },
          {
            "fieldPath": "affectedFile",
            "columnName": "affectedFile",
            "affinity": "TEXT",
            "notNull": false
          },
          {
            "fieldPath": "affectedLine",
            "columnName": "affectedLine",
            "affinity": "INTEGER",
            "notNull": false
          },
          {
            "fieldPath": "recommendation",
            "columnName": "recommendation",
            "affinity": "TEXT",
            "notNull": true
          },
          {
            "fieldPath": "cveId",
            "columnName": "cveId",
            "affinity": "TEXT",
            "notNull": false
          }
        ],
        "primaryKey": {
          "autoGenerate": false,
          "columnNames": [
            "scanId",
            "findingIndex"
          ]
        },
        "indices": [],
        "foreignKeys": []
      }
    ],
    "views": [],
    "setupQueries": [
      "CREATE TABLE IF NOT EXISTS room_master_table (id INTEGER PRIMARY KEY,identity_hash TEXT)",
      "INSERT OR REPLACE INTO room_master_table (id,identity_hash) VALUES(42, '87993c75a1c7106805064f9eed33c9aa')"
    ]
  }
}